{
  "parent": "minecraft:recipes/root",
  "rewards": {
    "recipes": [
      "vampirism:hunter/potion_table"
    ]
  },
  "criteria": {
    "has_glass_bottle": {
      "trigger": "minecraft:inventory_changed",
      "conditions": {
        "items": [
          {
            "items": [
              "minecraft:glass_bottle"
            ]
          }
        ]
      }
    },
    "has_the_recipe": {
      "trigger": "minecraft:recipe_unlocked",
      "conditions": {
        "recipe": "vampirism:hunter/potion_table"
      }
    }
  },
  "requirements": [
    [
      "has_glass_bottle",
      "has_the_recipe"
    ]
  ]
}