{
  "required": true,
  "package": "de.teamlapen.vampirism.mixin",
  "compatibilityLevel": "JAVA_17",
  "mixins": [
    "AreaEffectCloudMixin",
    "EntitySubPredicateMixin",
    "ItemMixin",
    "ItemStackMixin",
    "MixinBellBlock",
    "MixinEntity",
    "MixinEntityPredicate",
    "MixinJigsawPlacer",
    "MixinLivingEntity",
    "MixinMobEffectInstance",
    "MixinMobEntity",
    "MixinPlayerEntity",
    "MixinPotionBrewing",
    "NearestAttackableTargetGoalMixin",
    "NoiseGeneratorSettingsMixin",
    "ThrowablePotionMixin",
    "accessor.AbstractContainerMenuAccessor",
    "accessor.AbstractContainerScreenAccessor",
    "accessor.AbstractFurnaceBlockEntityAccessor",
    "accessor.AbstractFurnaceMenuAccessor",
    "accessor.ArmorItemAccessor",
    "accessor.AttributeInstanceAccessor",
    "accessor.BeaconBeamSectionyMixin",
    "accessor.BeaconBlockEntityMixin",
    "accessor.BlockFamiliesAccessor",
    "accessor.CrossbowItemMixin",
    "accessor.EntityAccessor",
    "accessor.EntitySubPredicateTypesAccessor",
    "accessor.GoalSelectorAccessor",
    "accessor.GroundPathNavigationAccessor",
    "accessor.IngredientAccessor",
    "accessor.ItemCombinerMenuAccessor",
    "accessor.LivingEntityAccessor",
    "accessor.LootTableAccessor",
    "accessor.MeleeAttackGoalAccessor",
    "accessor.MultiNoiseBiomeSourceParameterListPresetAccessor",
    "accessor.NearestAttackableTargetGoalAccessor",
    "accessor.ObjectiveCriteriaAccessor",
    "accessor.OrePlacementAccessor",
    "accessor.PlayerAdvancementsAccessor",
    "accessor.PotionBrewingAccessor",
    "accessor.ProcessorListsAccessor",
    "accessor.ProcessorRuleAccessor",
    "accessor.RecipeManagerAccessor",
    "accessor.RecipeProviderAccessor",
    "accessor.RegistriesDatapackGeneratorAccessor",
    "accessor.ReloadableServerResourcesAccessor",
    "accessor.ResourceKeyArgumentAccessor",
    "accessor.ShapedRecipeAccessor",
    "accessor.ShapedRecipeBuilderAccessor",
    "accessor.ShapelessRecipeBuilderAccessor",
    "accessor.SpawnStateAccessor",
    "accessor.SpreadingSnowyDirtBlockAccessor",
    "accessor.StructuresAccessor",
    "accessor.StructureTemplatePoolAccessor",
    "accessor.TagManagerAccessor",
    "accessor.TargetConditionAccessor",
    "accessor.TileEntityTypeAccessor",
    "accessor.VanillaBlockLootAccessor",
    "accessor.VillagerAccessor",
    "accessor.VillagerHostilesSensorAccessor",
    "accessor.WalkAnimationStateAccessor",
    "client.accessor.MobEffectAccessor"
  ],
  "client": [
    "client.HumanoidArmorLayerMixin",
    "client.LevelRendererMixin",
    "client.MinecraftMixin",
    "client.ResourceLoadStateTrackerMixin",
    "client.SheetsMixin",
    "client.StatsScreenMixin",
    "client.accessor.AgeableModelAccessor",
    "client.accessor.BossHealthOverlayAccessor",
    "client.accessor.BossOverlayGuiAccessor",
    "client.accessor.CameraAccessor",
    "client.accessor.EffectRenderingInventoryScreenAccessor",
    "client.accessor.HumanoidArmorLayerAccessor",
    "client.accessor.LivingEntityRendererAccessor",
    "client.accessor.ParticleEngineAccessor",
    "client.accessor.RecipeBookComponentAccessor",
    "client.accessor.RenderLayerAccessor",
    "client.accessor.StatsScreenAccessor",
    "client.accessor.VillagerModelAccessor"
  ],
  "injectors": {
    "defaultRequire": 1
  },
  "minVersion": "0.8.5"
}