{
  "credit": "Made with Blockbench",
  "parent": "minecraft:item/handheld",
  "textures": {
    "layer0": "vampirism:item/crucifix_iron"
  },
  "display": {
    "thirdperson_righthand": {
      "rotation": [
        30,
        0,
        0
      ],
      "translation": [
        0,
        1.5,
        1.25
      ],
      "scale": [
        0.7,
        0.7,
        0.7
      ]
    },
    "thirdperson_lefthand": {
      "rotation": [
        30,
        0,
        0
      ],
      "translation": [
        0,
        1.5,
        1.25
      ],
      "scale": [
        0.7,
        0.7,
        0.7
      ]
    },
    "firstperson_righthand": {
      "rotation": [
        0,
        -10,
        0
      ],
      "translation": [
        1.75,
        2,
        -3
      ],
      "scale": [
        0.7,
        0.7,
        0.7
      ]
    },
    "firstperson_lefthand": {
      "rotation": [
        0,
        -12.5,
        0
      ],
      "translation": [
        0,
        2,
        -3
      ],
      "scale": [
        0.7,
        0.7,
        0.7
      ]
    },
    "ground": {
      "translation": [
        0,
        0.5,
        0
      ],
      "scale": [
        0.5,
        0.5,
        0.5
      ]
    }
  }
}